{
    "hover": {
        "format" : "```\n${definition}\n```\n\n-------\n\nPredefined WinCC OA constant\n\nCommon Name Service\n\n${description}"
    },
    "completionItemKind": "Constant",
    "defines":[
        {
            "definition": "const int CNS_SEARCH_NAME = 1",
            "description": [
            ],
            "id": "CNS_SEARCH_NAME"
        },
        {
            "definition": "const int CNS_SEARCH_DISPLAY_NAME = 2",
            "description": [
            ],
            "id": "CNS_SEARCH_DISPLAY_NAME"
        },
        {
            "definition": "const int CNS_SEARCH_ALL_NAMES = 3",
            "description": [
            ],
            "id": "CNS_SEARCH_ALL_NAMES"
        },
        {
            "definition": "const int CNS_SEARCH_ALL_TYPES = 0",
            "description": [
            ],
            "id": "CNS_SEARCH_ALL_TYPES"
        },
        {
            "definition": "const int CNS_SEARCH_ALL_LANGUAGES = 255",
            "description": [
            ],
            "id": "CNS_SEARCH_ALL_LANGUAGES"
        },
        {
            "definition": "const int CNS_SEARCH_CASE_INSENSITIVE = 4",
            "description": [
            ],
            "id": "CNS_SEARCH_CASE_INSENSITIVE"
        },
        {
            "definition": "const int CNS_CHANGE_SYSTEM_NAMES = 0",
            "description": [
            ],
            "id": "CNS_CHANGE_SYSTEM_NAMES"
        },
        {
            "definition": "const int CNS_CHANGE_VIEW_SEPARATORS = 1",
            "description": [
            ],
            "id": "CNS_CHANGE_VIEW_SEPARATORS"
        },
        {
            "definition": "const int CNS_CHANGE_NAMES = 2",
            "description": [
            ],
            "id": "CNS_CHANGE_NAMES"
        },
        {
            "definition": "const int CNS_CHANGE_DATA = 3",
            "description": [
            ],
            "id": "CNS_CHANGE_DATA"
        },
        {
            "definition": "const int CNS_CHANGE_STRUCTURE = 4",
            "description": [
            ],
            "id": "CNS_CHANGE_STRUCTURE"
        },
        {
            "definition": "const int CNS_DATATYPE_ALL_TYPES = 0",
            "description": [
            ],
            "id": "CNS_DATATYPE_ALL_TYPES"
        },
        {
            "definition": "const int CNS_DATATYPE_EMPTY = 1",
            "description": [
            ],
            "id": "CNS_DATATYPE_EMPTY"
        },
        {
            "definition": "const int CNS_DATATYPE_DATAPOINT = 2",
            "description": [
            ],
            "id": "CNS_DATATYPE_DATAPOINT"
        },
        {
            "definition": "const int CNSSUB_SYS = 1",
            "description": [
            ],
            "id": "CNSSUB_SYS"
        },
        {
            "definition": "const int CNSSUB_VIEW = 2",
            "description": [
            ],
            "id": "CNSSUB_VIEW"
        },
        {
            "definition": "const int CNSSUB_PATH = 4",
            "description": [
            ],
            "id": "CNSSUB_PATH"
        },
        {
            "definition": "const int CNSSUB_PARENT = 8",
            "description": [
            ],
            "id": "CNSSUB_PARENT"
        },
        {
            "definition": "const int CNSSUB_ROOT = 16",
            "description": [
            ],
            "id": "CNSSUB_ROOT"
        },
        {
            "definition": "const int CNSSUB_NODE = 32",
            "description": [
            ],
            "id": "CNSSUB_NODE"
        },
        {
            "definition": "const int CNSSUB_TAIL = 64",
            "description": [
            ],
            "id": "CNSSUB_TAIL"
        }
    ]
}